build/lib/st_aggrid/frontend/build/asset-manifest.json
build/lib/st_aggrid/frontend/build/bootstrap.min.css
build/lib/st_aggrid/frontend/build/index.html
build/lib/st_aggrid/frontend/build/static/css/2.27e86a51.chunk.css
build/lib/st_aggrid/frontend/build/static/css/2.27e86a51.chunk.css.map
build/lib/st_aggrid/frontend/build/static/css/main.c37d4f9d.chunk.css
build/lib/st_aggrid/frontend/build/static/css/main.c37d4f9d.chunk.css.map
build/lib/st_aggrid/frontend/build/static/js/2.761ff4f8.chunk.js
build/lib/st_aggrid/frontend/build/static/js/2.761ff4f8.chunk.js.LICENSE.txt
build/lib/st_aggrid/frontend/build/static/js/2.761ff4f8.chunk.js.map
build/lib/st_aggrid/frontend/build/static/js/main.57cd8125.chunk.js
build/lib/st_aggrid/frontend/build/static/js/main.57cd8125.chunk.js.map
build/lib/st_aggrid/frontend/build/static/js/runtime-main.d9f6a119.js
build/lib/st_aggrid/frontend/build/static/js/runtime-main.d9f6a119.js.map
build/lib/st_aggrid_pro/frontend/build/asset-manifest.json
build/lib/st_aggrid_pro/frontend/build/bootstrap.min.css
build/lib/st_aggrid_pro/frontend/build/index.html
build/lib/st_aggrid_pro/frontend/build/static/css/2.058df4f5.chunk.css
build/lib/st_aggrid_pro/frontend/build/static/css/2.058df4f5.chunk.css.map
build/lib/st_aggrid_pro/frontend/build/static/css/2.27e86a51.chunk.css
build/lib/st_aggrid_pro/frontend/build/static/css/2.27e86a51.chunk.css.map
build/lib/st_aggrid_pro/frontend/build/static/css/2.c2821726.chunk.css
build/lib/st_aggrid_pro/frontend/build/static/css/2.c2821726.chunk.css.map
build/lib/st_aggrid_pro/frontend/build/static/css/main.43352fcf.chunk.css
build/lib/st_aggrid_pro/frontend/build/static/css/main.43352fcf.chunk.css.map
build/lib/st_aggrid_pro/frontend/build/static/css/main.8d4f52e2.css
build/lib/st_aggrid_pro/frontend/build/static/css/main.8d4f52e2.css.map
build/lib/st_aggrid_pro/frontend/build/static/css/main.99933db3.chunk.css
build/lib/st_aggrid_pro/frontend/build/static/css/main.99933db3.chunk.css.map
streamlit_aggrid_pro-0.3.35.dist-info/METADATA
streamlit_aggrid_pro-0.3.35.dist-info/WHEEL
streamlit_aggrid_pro-0.3.35.dist-info/RECORD
